snecs_functions/__init__.py
snecs_functions/snecs_functions.py
snecs_functions-0.0.0.dist-info/LICENSE
snecs_functions-0.0.0.dist-info/METADATA
snecs_functions-0.0.0.dist-info/WHEEL
snecs_functions-0.0.0.dist-info/top_level.txt
snecs_functions-0.0.0.dist-info/RECORD
