Metadata-Version: 2.1
Name: snecs_functions
Version: 0.0.0
Summary: Python package for working with the Sub-National Energy Consumption Statistics dataset
Author-email: Steven Firth <s.k.firth@lboro.ac.uk>
Project-URL: Homepage, https://github.com/building-energy/snecs_functions
Project-URL: Issues, https://github.com/building-energy/snecs_functions/issues
Classifier: Programming Language :: Python :: 3
Classifier: License :: OSI Approved :: MIT License
Classifier: Operating System :: OS Independent
Requires-Python: >=3.6
License-File: LICENSE
Requires-Dist: csvw-functions-extra >=0.0.0
